LICENSE
README.md
setup.py
MeleeUploader.egg-info/PKG-INFO
MeleeUploader.egg-info/SOURCES.txt
MeleeUploader.egg-info/dependency_links.txt
MeleeUploader.egg-info/entry_points.txt
MeleeUploader.egg-info/requires.txt
MeleeUploader.egg-info/top_level.txt
meleeuploader/__init__.py
meleeuploader/__main__.py
meleeuploader/client_secrets.json
meleeuploader/consts.py
meleeuploader/forms.py
meleeuploader/main.py
meleeuploader/utils.py
meleeuploader/viewers.py
meleeuploader/workers.py
meleeuploader/youtube.py
meleeuploader/obswebsocket/__init__.py
meleeuploader/obswebsocket/base_classes.py
meleeuploader/obswebsocket/core.py
meleeuploader/obswebsocket/events.py
meleeuploader/obswebsocket/exceptions.py
meleeuploader/obswebsocket/requests.py