Metadata-Version: 2.1
Name: MeleeUploader
Version: 1.22.0
Summary: A YouTube Uploader with Super Smash Bros. in mind
Home-page: https://github.com/NikhilNarayana/Melee-YouTube-Uploader
Author: Nikhil Narayana
Author-email: nikhil.narayana@live.com
License: GNU Public License v3.0
Keywords: smash melee ssbm ssbu ultimate youtube uploader
Platform: UNKNOWN
Classifier: Development Status :: 5 - Production/Stable
Classifier: Programming Language :: Python :: 3.7
Classifier: Operating System :: OS Independent
Classifier: License :: OSI Approved :: GNU General Public License v3 (GPLv3)
Classifier: Natural Language :: English
Requires-Python: >= 3.7.0
License-File: LICENSE
